LICENSE.txt
README.md
setup.cfg
setup.py
milliman_sensi/__init__.py
milliman_sensi/io.py
milliman_sensi/syntax.py
milliman_sensi/table_diff.py
milliman_sensi/utility.py
milliman_sensi.egg-info/PKG-INFO
milliman_sensi.egg-info/SOURCES.txt
milliman_sensi.egg-info/dependency_links.txt
milliman_sensi.egg-info/requires.txt
milliman_sensi.egg-info/top_level.txt