Metadata-Version: 2.1
Name: milliman-sensi
Version: 1.1.15
Summary: A parser and modifier of the configuration in Milliman-CHESS
Home-page: https://dev.azure.com/millimanparis/CHESS-Sensitivity-Manager
Author: Quincy HSIEH
Author-email: quincy.hsieh@milliman.com
License: MIT
Keywords: Milliman CHESS,configuration,parsers,sensitibity
Classifier: Development Status :: 3 - Alpha
Classifier: Intended Audience :: Developers
Classifier: Topic :: Software Development :: Build Tools
Classifier: License :: OSI Approved :: MIT License
Classifier: Programming Language :: Python
Classifier: Programming Language :: Python :: 3
Classifier: Programming Language :: Python :: 3.6
License-File: LICENSE.txt
